{"daily-log_apr2023.md":"e823b9be","notes_front-end_js-prototype.md":"f980029e","notes_front-end_css-bem.md":"0ff047e9","daily-log_jun2023.md":"fa8a6d35","daily-log_mar2023.md":"ee836af6","daily-log_jan2023.md":"b5ae925a","daily-log_dec2022.md":"d3b03bf0","daily-log_oct2022.md":"3f9ca4af","notes_misc_git-notes.md":"e2b7968f","notes_front-end_js-dom-api.md":"4ae92cd7","notes_misc_java-notes.md":"afd927b5","notes_misc_linux-notes.md":"6c36d5eb","notes_misc_ros-files.md":"f2d03be9","notes_misc_ros-notes.md":"332baa7c","index.md":"b5c15b44","notes_misc_python-notes.md":"5b864028","notes_front-end_tagfinder.md":"5bb121ed","notes_front-end_package-json.md":"bb38bb61","notes_front-end_js-promise.md":"69109fd4","daily-log_nov2022.md":"786e53de","notes_front-end_axios.md":"f264bab1","notes_misc_launch-notes.md":"9bd47059","daily-log_may2023.md":"ad7c3ec6","notes_front-end_js-dom-event.md":"af2d197a","notes_front-end_ts-notes.md":"31b91869","daily-log_feb2023.md":"08db872b","notes_front-end_type-challenges.md":"dc280f28","notes_front-end_vueuse-notes.md":"b15b8aa8","notes_misc_sql-notes.md":"23d25468","daily-log_sep2022.md":"356311a7"}
